petchouapplauncher/.DS_Store
petchouapplauncher/__main__.py
petchouapplauncher/assets/.DS_Store
petchouapplauncher/assets/back.png
petchouapplauncher/assets/black.png
petchouapplauncher/assets/mainIcon.png
petchouapplauncher/assets/morpionIcon.png
petchouapplauncher/assets/pythonLogo.png
petchouapplauncher-0.1.0.dist-info/WHEEL
petchouapplauncher-0.1.0.dist-info/METADATA
petchouapplauncher-0.1.0.dist-info/RECORD
